BatchManager/__init__.py
BatchManager/batch_manager.py
BatchManager-0.0.1.dist-info/LICENSE
BatchManager-0.0.1.dist-info/METADATA
BatchManager-0.0.1.dist-info/WHEEL
BatchManager-0.0.1.dist-info/top_level.txt
BatchManager-0.0.1.dist-info/RECORD
